mantis/__init__.py
mantis/__main__.py
mantis/__version.py
mantis/base.py
mantis/cli.py
mantis/client.py
mantis/const.py
mantis/exceptions.py
mantis/mixins.py
mantis/utils.py
mantis/_requests/__init__.py
mantis/_requests/mantis_requests.py
mantis/api/v1/__init__.py
mantis/api/v1/objects/__init__.py
mantis/api/v1/objects/attachment.py
mantis/api/v1/objects/config.py
mantis/api/v1/objects/filter.py
mantis/api/v1/objects/issue.py
mantis/api/v1/objects/note.py
mantis/api/v1/objects/project.py
mantis/api/v1/objects/user.py
python_mantis-0.6.dist-info/LICENSE
python_mantis-0.6.dist-info/METADATA
python_mantis-0.6.dist-info/WHEEL
python_mantis-0.6.dist-info/top_level.txt
python_mantis-0.6.dist-info/RECORD
